pdx2/__init__.py
pdx2/_data.py
pdx2/_io.py
pdx2/_pandas.py
pdx2/_query.py
pdx2/_util.py
pdx2/data/iris.csv
pdx2-0.11.0.dist-info/METADATA
pdx2-0.11.0.dist-info/WHEEL
pdx2-0.11.0.dist-info/licenses/LICENSE
pdx2-0.11.0.dist-info/RECORD
