Metadata-Version: 2.4
Name: pdx2
Version: 0.11.0
Summary: Helper functions to run SQL on Pandas DataFrames
Project-URL: homepage, https://github.com/ajfriend/pdx2
Project-URL: repository, https://github.com/ajfriend/pdx2
Project-URL: documentation, https://github.com/ajfriend/pdx2
Project-URL: pypi, https://pypi.org/project/pdx2
Author-email: AJ Friend <ajfriend@gmail.com>
License: BSD 3-Clause License
License-File: LICENSE
Keywords: ETL,SQL,data-wrangling,duckdb,pipelines
Requires-Python: >=3.9
Requires-Dist: duckdb>=1.0
Requires-Dist: pandas>=2.0
Requires-Dist: pyarrow>=15.0.0
Provides-Extra: test
Requires-Dist: pytest; extra == 'test'
Requires-Dist: pytest-cov; extra == 'test'
Requires-Dist: ruff; extra == 'test'
